{"buildTime":"2024-03-10T13:12:08.806Z","sources":[{"id":"FlameScans","name":"FlameScans","author":"NmN","desc":"Extension that pulls manga from Flame Scans.","website":"http://github.com/pandeynmm","contentRating":"EVERYONE","version":"3.0.0","icon":"icon.ico","tags":[{"text":"English","type":"info"},{"text":"Cloudflare","type":"danger"}],"websiteBaseURL":"https://flamescans.org","intents":21},{"id":"ReaperScans","name":"ReaperScans","author":"NmN","desc":"Reaperscans source for 0.8","website":"http://github.com/pandeynmm","contentRating":"EVERYONE","version":"4.0.0","icon":"icon.png","tags":[{"text":"English","type":"info"}],"websiteBaseURL":"https://reaperscans.com","intents":21},{"id":"ZeroScans","name":"Zero Scans","author":"NmN","desc":"Extension that pulls manga from bato.to","website":"http://github.com/pandeynmm","contentRating":"EVERYONE","version":"2.0.1","icon":"icon.png","tags":[{"text":"English","type":"info"}],"websiteBaseURL":"https://zscans.com","intents":21}],"builtWith":{"toolchain":"0.8.0-alpha.47","types":"0.8.0-alpha.47"}}